WebAppDIRAC/__init__.py
WebAppDIRAC/Core/App.py
WebAppDIRAC/Core/CoreHandler.py
WebAppDIRAC/Core/HandlerMgr.py
WebAppDIRAC/Core/StaticHandler.py
WebAppDIRAC/Core/TemplateLoader.py
WebAppDIRAC/Core/__init__.py
WebAppDIRAC/Lib/Conf.py
WebAppDIRAC/Lib/SessionData.py
WebAppDIRAC/Lib/WebHandler.py
WebAppDIRAC/Lib/__init__.py
WebAppDIRAC/WebApp/__init__.py
WebAppDIRAC/WebApp/web.cfg
WebAppDIRAC/WebApp/handler/AccountingHandler.py
WebAppDIRAC/WebApp/handler/ApplicationWizardHandler.py
WebAppDIRAC/WebApp/handler/ComponentHistoryHandler.py
WebAppDIRAC/WebApp/handler/ConfigurationManagerHandler.py
WebAppDIRAC/WebApp/handler/DowntimesHandler.py
WebAppDIRAC/WebApp/handler/ExampleAppHandler.py
WebAppDIRAC/WebApp/handler/FileCatalogHandler.py
WebAppDIRAC/WebApp/handler/JobLaunchpadHandler.py
WebAppDIRAC/WebApp/handler/JobMonitorHandler.py
WebAppDIRAC/WebApp/handler/JobSummaryHandler.py
WebAppDIRAC/WebApp/handler/MonitoringHandler.py
WebAppDIRAC/WebApp/handler/NotepadHandler.py
WebAppDIRAC/WebApp/handler/PilotMonitorHandler.py
WebAppDIRAC/WebApp/handler/PilotSummaryHandler.py
WebAppDIRAC/WebApp/handler/ProxyManagerHandler.py
WebAppDIRAC/WebApp/handler/ProxyUploadHandler.py
WebAppDIRAC/WebApp/handler/PublicStateManagerHandler.py
WebAppDIRAC/WebApp/handler/RegistryManagerHandler.py
WebAppDIRAC/WebApp/handler/RequestMonitorHandler.py
WebAppDIRAC/WebApp/handler/ResourceSummaryHandler.py
WebAppDIRAC/WebApp/handler/RootHandler.py
WebAppDIRAC/WebApp/handler/SiteSummaryHandler.py
WebAppDIRAC/WebApp/handler/SpaceOccupancyHandler.py
WebAppDIRAC/WebApp/handler/SystemAdministrationHandler.py
WebAppDIRAC/WebApp/handler/TokenManagerHandler.py
WebAppDIRAC/WebApp/handler/TransformationMonitorHandler.py
WebAppDIRAC/WebApp/handler/UPHandler.py
WebAppDIRAC/WebApp/handler/VMDiracHandler.py
WebAppDIRAC/WebApp/handler/__init__.py
WebAppDIRAC/WebApp/static/DIRAC/Accounting/build/Accounting.js
WebAppDIRAC/WebApp/static/DIRAC/Accounting/build/Accounting.js.gz
WebAppDIRAC-5.0.12.dist-info/LICENSE
WebAppDIRAC-5.0.12.dist-info/METADATA
WebAppDIRAC-5.0.12.dist-info/WHEEL
WebAppDIRAC-5.0.12.dist-info/entry_points.txt
WebAppDIRAC-5.0.12.dist-info/top_level.txt
WebAppDIRAC-5.0.12.dist-info/RECORD
